{
    "resource": "drafthistory",
    "parameters": {
        "LeagueID": "00",
        "Season": "2011",
        "TeamID": null,
        "RoundNum": 1,
        "RoundPick": null,
        "OverallPick": null,
        "TopX": null,
        "College": null
    },
    "resultSets": [
        {
            "name": "DraftHistory",
            "headers": [
                "PERSON_ID",
                "PLAYER_NAME",
                "SEASON",
                "ROUND_NUMBER",
                "ROUND_PICK",
                "OVERALL_PICK",
                "TEAM_ID",
                "TEAM_CITY",
                "TEAM_NAME",
                "TEAM_ABBREVIATION",
                "ORGANIZATION",
                "ORGANIZATION_TYPE"
            ],
            "rowSet": [
                [
                    202681,
                    "Kyrie Irving",
                    "2011",
                    1,
                    1,
                    1,
                    1610612739,
                    "Cleveland",
                    "Cavaliers",
                    "CLE",
                    "Duke",
                    "College/University"
                ],
                [
                    202682,
                    "Derrick Williams",
                    "2011",
                    1,
                    2,
                    2,
                    1610612750,
                    "Minnesota",
                    "Timberwolves",
                    "MIN",
                    "Arizona",
                    "College/University"
                ],
                [
                    202683,
                    "Enes Kanter",
                    "2011",
                    1,
                    3,
                    3,
                    1610612762,
                    "Utah",
                    "Jazz",
                    "UTA",
                    "Kentucky",
                    "College/University"
                ],
                [
                    202684,
                    "Tristan Thompson",
                    "2011",
                    1,
                    4,
                    4,
                    1610612739,
                    "Cleveland",
                    "Cavaliers",
                    "CLE",
                    "Texas",
                    "College/University"
                ],
                [
                    202685,
                    "Jonas Valanciunas",
                    "2011",
                    1,
                    5,
                    5,
                    1610612761,
                    "Toronto",
                    "Raptors",
                    "TOR",
                    "BC Lietuvos rytas",
                    "Other Team/Club"
                ],
                [
                    202686,
                    "Jan Vesely",
                    "2011",
                    1,
                    6,
                    6,
                    1610612764,
                    "Washington",
                    "Wizards",
                    "WAS",
                    "Belgrade Serbia",
                    "Other Team/Club"
                ],
                [
                    202687,
                    "Bismack Biyombo",
                    "2011",
                    1,
                    7,
                    7,
                    1610612758,
                    "Sacramento",
                    "Kings",
                    "SAC",
                    "Baloncesto Fuenlabrada (Spain)",
                    "Other Team/Club"
                ],
                [
                    202688,
                    "Brandon Knight",
                    "2011",
                    1,
                    8,
                    8,
                    1610612765,
                    "Detroit",
                    "Pistons",
                    "DET",
                    "Kentucky",
                    "College/University"
                ],
                [
                    202689,
                    "Kemba Walker",
                    "2011",
                    1,
                    9,
                    9,
                    1610612766,
                    "Charlotte",
                    "Bobcats",
                    "CHA",
                    "Connecticut",
                    "College/University"
                ],
                [
                    202690,
                    "Jimmer Fredette",
                    "2011",
                    1,
                    10,
                    10,
                    1610612749,
                    "Milwaukee",
                    "Bucks",
                    "MIL",
                    "Brigham Young",
                    "College/University"
                ],
                [
                    202691,
                    "Klay Thompson",
                    "2011",
                    1,
                    11,
                    11,
                    1610612744,
                    "Golden State",
                    "Warriors",
                    "GSW",
                    "Washington State",
                    "College/University"
                ],
                [
                    202692,
                    "Alec Burks",
                    "2011",
                    1,
                    12,
                    12,
                    1610612762,
                    "Utah",
                    "Jazz",
                    "UTA",
                    "Colorado",
                    "College/University"
                ],
                [
                    202693,
                    "Markieff Morris",
                    "2011",
                    1,
                    13,
                    13,
                    1610612756,
                    "Phoenix",
                    "Suns",
                    "PHX",
                    "Kansas",
                    "College/University"
                ],
                [
                    202694,
                    "Marcus Morris",
                    "2011",
                    1,
                    14,
                    14,
                    1610612745,
                    "Houston",
                    "Rockets",
                    "HOU",
                    "Kansas",
                    "College/University"
                ],
                [
                    202695,
                    "Kawhi Leonard",
                    "2011",
                    1,
                    15,
                    15,
                    1610612754,
                    "Indiana",
                    "Pacers",
                    "IND",
                    "San Diego State",
                    "College/University"
                ],
                [
                    202696,
                    "Nikola Vucevic",
                    "2011",
                    1,
                    16,
                    16,
                    1610612755,
                    "Philadelphia",
                    "76ers",
                    "PHI",
                    "Southern California",
                    "College/University"
                ],
                [
                    202697,
                    "Iman Shumpert",
                    "2011",
                    1,
                    17,
                    17,
                    1610612752,
                    "New York",
                    "Knicks",
                    "NYK",
                    "Georgia Tech",
                    "College/University"
                ],
                [
                    202698,
                    "Chris Singleton",
                    "2011",
                    1,
                    18,
                    18,
                    1610612764,
                    "Washington",
                    "Wizards",
                    "WAS",
                    "Florida State",
                    "College/University"
                ],
                [
                    202699,
                    "Tobias Harris",
                    "2011",
                    1,
                    19,
                    19,
                    1610612766,
                    "Charlotte",
                    "Bobcats",
                    "CHA",
                    "Tennessee",
                    "College/University"
                ],
                [
                    202700,
                    "Donatas Motiejunas",
                    "2011",
                    1,
                    20,
                    20,
                    1610612750,
                    "Minnesota",
                    "Timberwolves",
                    "MIN",
                    "Universo Treviso Basket (Italy)",
                    "Other Team/Club"
                ],
                [
                    202701,
                    "Nolan Smith",
                    "2011",
                    1,
                    21,
                    21,
                    1610612757,
                    "Portland",
                    "Trail Blazers",
                    "POR",
                    "Duke",
                    "College/University"
                ],
                [
                    202702,
                    "Kenneth Faried",
                    "2011",
                    1,
                    22,
                    22,
                    1610612743,
                    "Denver",
                    "Nuggets",
                    "DEN",
                    "Morehead State",
                    "College/University"
                ],
                [
                    202703,
                    "Nikola Mirotic",
                    "2011",
                    1,
                    23,
                    23,
                    1610612745,
                    "Houston",
                    "Rockets",
                    "HOU",
                    "Real Madrid Baloncesto (Spain)",
                    "Other Team/Club"
                ],
                [
                    202704,
                    "Reggie Jackson",
                    "2011",
                    1,
                    24,
                    24,
                    1610612760,
                    "Oklahoma City",
                    "Thunder",
                    "OKC",
                    "Boston College",
                    "College/University"
                ],
                [
                    202705,
                    "MarShon Brooks",
                    "2011",
                    1,
                    25,
                    25,
                    1610612738,
                    "Boston",
                    "Celtics",
                    "BOS",
                    "Providence",
                    "College/University"
                ],
                [
                    202706,
                    "Jordan Hamilton",
                    "2011",
                    1,
                    26,
                    26,
                    1610612742,
                    "Dallas",
                    "Mavericks",
                    "DAL",
                    "Texas",
                    "College/University"
                ],
                [
                    202707,
                    "JaJuan Johnson",
                    "2011",
                    1,
                    27,
                    27,
                    1610612751,
                    "New Jersey",
                    "Nets",
                    "NJN",
                    "Purdue",
                    "College/University"
                ],
                [
                    202708,
                    "Norris Cole",
                    "2011",
                    1,
                    28,
                    28,
                    1610612741,
                    "Chicago",
                    "Bulls",
                    "CHI",
                    "Cleveland State",
                    "College/University"
                ],
                [
                    202709,
                    "Cory Joseph",
                    "2011",
                    1,
                    29,
                    29,
                    1610612759,
                    "San Antonio",
                    "Spurs",
                    "SAS",
                    "Texas",
                    "College/University"
                ],
                [
                    202710,
                    "Jimmy Butler",
                    "2011",
                    1,
                    30,
                    30,
                    1610612741,
                    "Chicago",
                    "Bulls",
                    "CHI",
                    "Marquette",
                    "College/University"
                ]
            ]
        }
    ]
}